{
  "url": "http://localhost:4322/services/ascend",
  "pathname": "/services/ascend",
  "title": "Ascend — The Installed AI Growth System Buildwise Runs",
  "viewport": {
    "width": 768,
    "height": 1024
  },
  "document": {
    "scrollWidth": 768,
    "scrollHeight": 7994,
    "overflowX": 0
  },
  "h1s": [
    "The installed AI growth system Buildwise runs for you."
  ],
  "exactCtas": [
    {
      "tag": "a",
      "type": "",
      "text": "See If We're a Fit→",
      "href": "/book",
      "ctaSource": "ascend-hero",
      "rect": {
        "top": -374,
        "left": 38,
        "width": 219,
        "height": 64,
        "bottom": -310,
        "right": 257,
        "absTop": 400,
        "absBottom": 464
      },
      "clippedX": false,
      "clippedY": false
    },
    {
      "tag": "a",
      "type": "",
      "text": "See If We're a Fit→",
      "href": "/book",
      "ctaSource": "ascend-final",
      "rect": {
        "top": 6309,
        "left": 38,
        "width": 219,
        "height": 64,
        "bottom": 6373,
        "right": 257,
        "absTop": 7083,
        "absBottom": 7147
      },
      "clippedX": false,
      "clippedY": false
    },
    {
      "tag": "a",
      "type": "",
      "text": "Book a discovery call",
      "href": "/book",
      "ctaSource": "",
      "rect": {
        "top": 6761,
        "left": 279,
        "width": 143,
        "height": 19,
        "bottom": 6780,
        "right": 422,
        "absTop": 7535,
        "absBottom": 7554
      },
      "clippedX": false,
      "clippedY": false
    },
    {
      "tag": "a",
      "type": "",
      "text": "Send us a message",
      "href": "/book",
      "ctaSource": "",
      "rect": {
        "top": 6840,
        "left": 279,
        "width": 134,
        "height": 19,
        "bottom": 6859,
        "right": 413,
        "absTop": 7614,
        "absBottom": 7633
      },
      "clippedX": false,
      "clippedY": false
    }
  ],
  "firstInteractive": [
    {
      "tag": "a",
      "type": "",
      "text": "Skip to content",
      "href": "#main",
      "ctaSource": "",
      "rect": {
        "top": -874,
        "left": 16,
        "width": 173,
        "height": 46,
        "bottom": -828,
        "right": 189,
        "absTop": -100,
        "absBottom": -54
      },
      "clippedX": false,
      "clippedY": false
    },
    {
      "tag": "a",
      "type": "",
      "text": "",
      "href": "/",
      "ctaSource": "",
      "rect": {
        "top": 20,
        "left": 38,
        "width": 128,
        "height": 32,
        "bottom": 52,
        "right": 166,
        "absTop": 794,
        "absBottom": 826
      },
      "clippedX": false,
      "clippedY": false
    },
    {
      "tag": "button",
      "type": "",
      "text": "",
      "href": "",
      "ctaSource": "",
      "rect": {
        "top": 16,
        "left": 690,
        "width": 40,
        "height": 40,
        "bottom": 56,
        "right": 730,
        "absTop": 790,
        "absBottom": 830
      },
      "clippedX": false,
      "clippedY": false
    },
    {
      "tag": "a",
      "type": "",
      "text": "See If We're a Fit→",
      "href": "/book",
      "ctaSource": "ascend-hero",
      "rect": {
        "top": -374,
        "left": 38,
        "width": 219,
        "height": 64,
        "bottom": -310,
        "right": 257,
        "absTop": 400,
        "absBottom": 464
      },
      "clippedX": false,
      "clippedY": false
    },
    {
      "tag": "a",
      "type": "",
      "text": "See What's Inside",
      "href": "#layers",
      "ctaSource": "ascend-hero-secondary",
      "rect": {
        "top": -374,
        "left": 273,
        "width": 197,
        "height": 64,
        "bottom": -310,
        "right": 470,
        "absTop": 400,
        "absBottom": 464
      },
      "clippedX": false,
      "clippedY": false
    },
    {
      "tag": "a",
      "type": "",
      "text": "See full pricing→",
      "href": "/pricing",
      "ctaSource": "ascend-pricing",
      "rect": {
        "top": 5900,
        "left": 38,
        "width": 194,
        "height": 64,
        "bottom": 5964,
        "right": 233,
        "absTop": 6674,
        "absBottom": 6738
      },
      "clippedX": false,
      "clippedY": false
    },
    {
      "tag": "a",
      "type": "",
      "text": "See If We're a Fit→",
      "href": "/book",
      "ctaSource": "ascend-final",
      "rect": {
        "top": 6309,
        "left": 38,
        "width": 219,
        "height": 64,
        "bottom": 6373,
        "right": 257,
        "absTop": 7083,
        "absBottom": 7147
      },
      "clippedX": false,
      "clippedY": false
    },
    {
      "tag": "a",
      "type": "",
      "text": "",
      "href": "/",
      "ctaSource": "",
      "rect": {
        "top": 6518,
        "left": 38,
        "width": 120,
        "height": 30,
        "bottom": 6548,
        "right": 158,
        "absTop": 7292,
        "absBottom": 7322
      },
      "clippedX": false,
      "clippedY": false
    },
    {
      "tag": "a",
      "type": "",
      "text": "Ascend",
      "href": "/services/ascend",
      "ctaSource": "",
      "rect": {
        "top": 6681,
        "left": 38,
        "width": 51,
        "height": 19,
        "bottom": 6700,
        "right": 89,
        "absTop": 7455,
        "absBottom": 7474
      },
      "clippedX": false,
      "clippedY": false
    },
    {
      "tag": "a",
      "type": "",
      "text": "The System",
      "href": "/system",
      "ctaSource": "",
      "rect": {
        "top": 6721,
        "left": 38,
        "width": 81,
        "height": 19,
        "bottom": 6740,
        "right": 119,
        "absTop": 7495,
        "absBottom": 7514
      },
      "clippedX": false,
      "clippedY": false
    },
    {
      "tag": "a",
      "type": "",
      "text": "How It Works",
      "href": "/how-it-works",
      "ctaSource": "",
      "rect": {
        "top": 6761,
        "left": 38,
        "width": 89,
        "height": 19,
        "bottom": 6780,
        "right": 128,
        "absTop": 7535,
        "absBottom": 7554
      },
      "clippedX": false,
      "clippedY": false
    },
    {
      "tag": "a",
      "type": "",
      "text": "Pricing",
      "href": "/pricing",
      "ctaSource": "",
      "rect": {
        "top": 6800,
        "left": 38,
        "width": 46,
        "height": 19,
        "bottom": 6819,
        "right": 84,
        "absTop": 7574,
        "absBottom": 7593
      },
      "clippedX": false,
      "clippedY": false
    }
  ],
  "clippedControls": [],
  "images": {
    "visibleCount": 5,
    "aboveFoldCount": 2,
    "broken": []
  },
  "mobileCtaWithin580": true,
  "headingQuality": {
    "issues": []
  },
  "cropSafety": {
    "issues": []
  },
  "sliderAffordance": [],
  "curveMarkers": []
}