{
  "url": "http://localhost:4321/system",
  "pathname": "/system",
  "title": "The Installed AI Growth System — Buildwise Media",
  "viewport": {
    "width": 768,
    "height": 1024
  },
  "document": {
    "scrollWidth": 768,
    "scrollHeight": 10086,
    "overflowX": 0
  },
  "h1s": [
    "See the AI growth system installed inside your business."
  ],
  "exactCtas": [
    {
      "tag": "a",
      "type": "",
      "text": "See If We're a Fit→",
      "href": "/book",
      "ctaSource": "system-hero",
      "rect": {
        "top": -1376,
        "left": 38,
        "width": 219,
        "height": 64,
        "bottom": -1312,
        "right": 257,
        "absTop": 400,
        "absBottom": 464
      },
      "clippedX": false,
      "clippedY": false
    },
    {
      "tag": "a",
      "type": "",
      "text": "See If We're a Fit →",
      "href": "/book",
      "ctaSource": "calculator-cta",
      "rect": {
        "top": 6925,
        "left": 38,
        "width": 219,
        "height": 64,
        "bottom": 6990,
        "right": 257,
        "absTop": 8701,
        "absBottom": 8766
      },
      "clippedX": false,
      "clippedY": false
    },
    {
      "tag": "a",
      "type": "",
      "text": "See If We're a Fit→",
      "href": "/book",
      "ctaSource": "system-final",
      "rect": {
        "top": 7383,
        "left": 38,
        "width": 219,
        "height": 64,
        "bottom": 7447,
        "right": 257,
        "absTop": 9159,
        "absBottom": 9223
      },
      "clippedX": false,
      "clippedY": false
    },
    {
      "tag": "a",
      "type": "",
      "text": "Book a discovery call",
      "href": "/book",
      "ctaSource": "",
      "rect": {
        "top": 7851,
        "left": 279,
        "width": 143,
        "height": 19,
        "bottom": 7870,
        "right": 422,
        "absTop": 9627,
        "absBottom": 9646
      },
      "clippedX": false,
      "clippedY": false
    },
    {
      "tag": "a",
      "type": "",
      "text": "Send us a message",
      "href": "/book",
      "ctaSource": "",
      "rect": {
        "top": 7930,
        "left": 279,
        "width": 134,
        "height": 19,
        "bottom": 7949,
        "right": 413,
        "absTop": 9706,
        "absBottom": 9725
      },
      "clippedX": false,
      "clippedY": false
    }
  ],
  "firstInteractive": [
    {
      "tag": "a",
      "type": "",
      "text": "Skip to content",
      "href": "#main",
      "ctaSource": "",
      "rect": {
        "top": -1876,
        "left": 16,
        "width": 173,
        "height": 46,
        "bottom": -1830,
        "right": 189,
        "absTop": -100,
        "absBottom": -54
      },
      "clippedX": false,
      "clippedY": false
    },
    {
      "tag": "a",
      "type": "",
      "text": "",
      "href": "/",
      "ctaSource": "",
      "rect": {
        "top": 20,
        "left": 38,
        "width": 128,
        "height": 32,
        "bottom": 52,
        "right": 166,
        "absTop": 1796,
        "absBottom": 1828
      },
      "clippedX": false,
      "clippedY": false
    },
    {
      "tag": "button",
      "type": "",
      "text": "",
      "href": "",
      "ctaSource": "",
      "rect": {
        "top": 16,
        "left": 690,
        "width": 40,
        "height": 40,
        "bottom": 56,
        "right": 730,
        "absTop": 1792,
        "absBottom": 1832
      },
      "clippedX": false,
      "clippedY": false
    },
    {
      "tag": "a",
      "type": "",
      "text": "See If We're a Fit→",
      "href": "/book",
      "ctaSource": "system-hero",
      "rect": {
        "top": -1376,
        "left": 38,
        "width": 219,
        "height": 64,
        "bottom": -1312,
        "right": 257,
        "absTop": 400,
        "absBottom": 464
      },
      "clippedX": false,
      "clippedY": false
    },
    {
      "tag": "a",
      "type": "",
      "text": "See Pricing",
      "href": "/pricing",
      "ctaSource": "system-pricing",
      "rect": {
        "top": -1376,
        "left": 273,
        "width": 146,
        "height": 64,
        "bottom": -1312,
        "right": 419,
        "absTop": 400,
        "absBottom": 464
      },
      "clippedX": false,
      "clippedY": false
    },
    {
      "tag": "input",
      "type": "range",
      "text": "20",
      "href": "",
      "ctaSource": "",
      "rect": {
        "top": 6385,
        "left": 67,
        "width": 192,
        "height": 3,
        "bottom": 6388,
        "right": 260,
        "absTop": 8161,
        "absBottom": 8164
      },
      "clippedX": false,
      "clippedY": true
    },
    {
      "tag": "input",
      "type": "range",
      "text": "8000",
      "href": "",
      "ctaSource": "",
      "rect": {
        "top": 6385,
        "left": 288,
        "width": 192,
        "height": 3,
        "bottom": 6388,
        "right": 480,
        "absTop": 8161,
        "absBottom": 8164
      },
      "clippedX": false,
      "clippedY": true
    },
    {
      "tag": "input",
      "type": "range",
      "text": "22",
      "href": "",
      "ctaSource": "",
      "rect": {
        "top": 6385,
        "left": 508,
        "width": 192,
        "height": 3,
        "bottom": 6388,
        "right": 701,
        "absTop": 8161,
        "absBottom": 8164
      },
      "clippedX": false,
      "clippedY": true
    },
    {
      "tag": "a",
      "type": "",
      "text": "See If We're a Fit →",
      "href": "/book",
      "ctaSource": "calculator-cta",
      "rect": {
        "top": 6925,
        "left": 38,
        "width": 219,
        "height": 64,
        "bottom": 6990,
        "right": 257,
        "absTop": 8701,
        "absBottom": 8766
      },
      "clippedX": false,
      "clippedY": false
    },
    {
      "tag": "a",
      "type": "",
      "text": "See If We're a Fit→",
      "href": "/book",
      "ctaSource": "system-final",
      "rect": {
        "top": 7383,
        "left": 38,
        "width": 219,
        "height": 64,
        "bottom": 7447,
        "right": 257,
        "absTop": 9159,
        "absBottom": 9223
      },
      "clippedX": false,
      "clippedY": false
    },
    {
      "tag": "a",
      "type": "",
      "text": "",
      "href": "/",
      "ctaSource": "",
      "rect": {
        "top": 7608,
        "left": 38,
        "width": 120,
        "height": 30,
        "bottom": 7638,
        "right": 158,
        "absTop": 9384,
        "absBottom": 9414
      },
      "clippedX": false,
      "clippedY": false
    },
    {
      "tag": "a",
      "type": "",
      "text": "Ascend",
      "href": "/services/ascend",
      "ctaSource": "",
      "rect": {
        "top": 7772,
        "left": 38,
        "width": 51,
        "height": 19,
        "bottom": 7791,
        "right": 89,
        "absTop": 9548,
        "absBottom": 9567
      },
      "clippedX": false,
      "clippedY": false
    }
  ],
  "clippedControls": [],
  "images": {
    "visibleCount": 5,
    "aboveFoldCount": 0,
    "broken": []
  },
  "mobileCtaWithin580": true,
  "headingQuality": {
    "issues": []
  },
  "cropSafety": {
    "issues": []
  },
  "sliderAffordance": [
    {
      "index": 0,
      "rangeCount": 3,
      "visibleOutputCount": 3,
      "rangeLabelSetCount": 3,
      "hasInstruction": true,
      "issues": []
    }
  ],
  "curveMarkers": []
}